unreal_ini_parser/__init__.py
unreal_ini_parser/exceptions.py
unreal_ini_parser/ini_parser.py
unreal_ini_parser-1.0.2.dist-info/METADATA
unreal_ini_parser-1.0.2.dist-info/WHEEL
unreal_ini_parser-1.0.2.dist-info/licenses/LICENSE
unreal_ini_parser-1.0.2.dist-info/RECORD
