Metadata-Version: 2.1
Name: unreal_ini_parser
Version: 1.0.2
Summary: Parser for Unreal Engine config files.
Project-URL: Homepage, https://github.com/ColdSpirit0/unreal_ini_parser
Project-URL: Issues, https://github.com/ColdSpirit0/unreal_ini_parser/issues
Author: ColdSpirit
License:                     GNU AFFERO GENERAL PUBLIC LICENSE
License-File: LICENSE
Classifier: License :: OSI Approved :: GNU Affero General Public License v3
Classifier: Operating System :: OS Independent
Classifier: Programming Language :: Python :: 3
Requires-Python: >=3.12
Requires-Dist: pathvalidate==3.2.0
